detective/__init__.py
detective/communication/__init__.py
detective/communication/client.py
detective/communication/mailbot.py
detective/communication/server.py
detective/modules/__init__.py
detective/modules/common.py
detective/modules/detect_others.py
detective/modules/gesture.py
detective/modules/gpio_controller.py
detective/modules/meditation_assistant - 副本.py
detective/modules/meditation_assistant.py
detective/modules/music_player.py
detective/modules/utils.py
detective/runner/__init__.py
detective/runner/music_engine.py
detective/runner/runner_engine.py
detective/runner/state_machine.py
Thread_Everything-0.3.0.dist-info/LICENSE
Thread_Everything-0.3.0.dist-info/METADATA
Thread_Everything-0.3.0.dist-info/WHEEL
Thread_Everything-0.3.0.dist-info/top_level.txt
Thread_Everything-0.3.0.dist-info/RECORD
