Metadata-Version: 2.1
Name: Thread-Everything
Version: 0.3.0
Summary: An easy-to-use interface to run threads from different machines
Home-page: https://sergiudm.github.io/Thread-Everything/
Author: Sergiu Han, Jihan Li
Author-email: sergiudm@outlook.com, 12211820@mail.sustech.edu.cn
Classifier: Programming Language :: Python :: 3
Classifier: License :: OSI Approved :: Apache Software License
Classifier: Operating System :: OS Independent
Requires-Python: >=3.10
License-File: LICENSE
Requires-Dist: opencv-python
Requires-Dist: opencv-python-headless
Requires-Dist: mediapipe
Requires-Dist: pygame
